README.md
setup.py
ServerCL/__init__.py
ServerCL.egg-info/PKG-INFO
ServerCL.egg-info/SOURCES.txt
ServerCL.egg-info/dependency_links.txt
ServerCL.egg-info/top_level.txt
ServerCL/Constant/Const.py
ServerCL/Constant/Variables.py
ServerCL/Constant/__init__.py
ServerCL/Response/Packer.py
ServerCL/Response/__init__.py
ServerCL/Server/Server.py
ServerCL/Server/__init__.py
ServerCL/ServerClient/ServerClient.py
ServerCL/ServerClient/__init__.py